README.md
setup.cfg
setup.py
napchart/__init__.py
napchart/main.py
napchart.egg-info/PKG-INFO
napchart.egg-info/SOURCES.txt
napchart.egg-info/dependency_links.txt
napchart.egg-info/requires.txt
napchart.egg-info/top_level.txt